{"meta":{"title":"","description":"","theme":"default","adid":"","sponsorMobile":"no","inSponsor":"no","hideDownloadButton":"no","fileTime":201904182151,"hideAd":"no","audiencePixelTag":"","guideline":"","showrighttype":"Poster"},"sections":[{"type":"Poster","name":"Poster 1","PosterLayout":"center","PosterTheme":"dark-blue","PosterBGImage":"124","PosterMainImage":"112","ClientLogo":"222","EventDate":"2223","EventDatePrefix":"2323","TitleWidth":"380","FirstTitle":"","FirstTitleFont":"38","SecondTitle":"","SecondTitleFont":"31","SubTitle":"","SubTitleFont":"22","QRUrl":"","QRTitle":"","note":""},{"type":"Poster","name":"Poster 2","PosterLayout":"center","PosterTheme":"dark-blue","PosterBGImage":"124","PosterMainImage":"112","ClientLogo":"222","EventDate":"2223","EventDatePrefix":"2323","TitleWidth":"380","FirstTitle":"","FirstTitleFont":"38","SecondTitle":"","SecondTitleFont":"31","SubTitle":"","SubTitleFont":"22","QRUrl":"","QRTitle":"","note":""},{"type":"Poster","name":"Poster 3","PosterLayout":"center","PosterTheme":"dark-blue","PosterBGImage":"124","PosterMainImage":"112","ClientLogo":"222","EventDate":"2223","EventDatePrefix":"2323","TitleWidth":"380","FirstTitle":"","FirstTitleFont":"38","SecondTitle":"","SecondTitleFont":"31","SubTitle":"","SubTitleFont":"22","QRUrl":"","QRTitle":"","note":""},{"type":"Poster","name":"Poster 4","PosterLayout":"center","PosterTheme":"dark-blue","PosterBGImage":"123","PosterMainImage":"112","ClientLogo":"222","EventDate":"2223","EventDatePrefix":"2323","TitleWidth":"380","FirstTitle":"","FirstTitleFont":"30","SecondTitle":"","SecondTitleFont":"31","SubTitle":"","SubTitleFont":"22","QRUrl":"","QRTitle":"","note":""}]}